guirlande_hub_client_package/__init__.py
guirlande_hub_client_package/ghc.py
guirlande_hub_client-1.0.0.dist-info/LICENCE
guirlande_hub_client-1.0.0.dist-info/METADATA
guirlande_hub_client-1.0.0.dist-info/WHEEL
guirlande_hub_client-1.0.0.dist-info/top_level.txt
guirlande_hub_client-1.0.0.dist-info/RECORD
